__init__.py
epydz.py
epydz-1.0.0.dist-info/LICENSE.txt
epydz-1.0.0.dist-info/METADATA
epydz-1.0.0.dist-info/WHEEL
epydz-1.0.0.dist-info/top_level.txt
epydz-1.0.0.dist-info/RECORD
