Metadata-Version: 2.1
Name: epydz
Version: 1.0.0
Summary: A Python library containing useful functions in the Algerian language
Author: talbi mohamed,alexmm
Author-email: monwin966@gmail.com
Keywords: Algerian,language,library,useful,functions
Classifier: Programming Language :: Python :: 3
Classifier: License :: OSI Approved :: MIT License
Classifier: Operating System :: Microsoft :: Windows :: Windows 10
Requires-Python: >=3.0
License-File: LICENSE.txt
